{
  "chapters": {
    "1": {
      "pendingViews": 1,
      "lastIncrement": "2025-12-19T22:33:03.913Z",
      "lastUpdate": "2025-12-19T00:21:40+07:00"
    },
    "2": {
      "pendingViews": 1,
      "lastIncrement": "2025-12-19T22:37:11.977Z",
      "lastUpdate": "2025-12-19T00:21:40+07:00"
    },
    "3": {
      "pendingViews": 1,
      "lastIncrement": "2025-12-19T22:39:24.714Z",
      "lastUpdate": "2025-12-19T00:21:40+07:00"
    },
    "4": {
      "pendingViews": 1,
      "lastIncrement": "2025-12-19T22:41:26.919Z",
      "lastUpdate": "2025-12-20T00:17:53+07:00"
    },
    "7": {
      "pendingViews": 5,
      "lastIncrement": "2025-12-19T21:23:48.301Z",
      "lastUpdate": "2025-12-20T00:17:53+07:00"
    },
    "5.1": {
      "pendingViews": 1,
      "lastIncrement": "2025-12-19T22:43:01.334Z",
      "lastUpdate": "2025-12-19T00:21:40+07:00"
    },
    "5.2": {
      "pendingViews": 1,
      "lastIncrement": "2025-12-19T22:45:35.089Z",
      "lastUpdate": "2025-12-19T00:21:40+07:00"
    },
    "5.5": {
      "pendingViews": 2,
      "lastIncrement": "2025-12-19T22:47:41.465Z",
      "lastUpdate": "2025-12-19T00:21:40+07:00"
    },
    "6.1": {
      "pendingViews": 1,
      "lastIncrement": "2025-12-19T22:50:09.927Z",
      "lastUpdate": "2025-12-19T00:21:40+07:00"
    },
    "6.2": {
      "pendingViews": 1,
      "lastIncrement": "2025-12-19T17:23:43.292Z",
      "lastUpdate": "2025-12-20T00:17:53+07:00"
    }
  },
  "lastUpdated": "2025-12-20T00:17:53+07:00"
}