{
  "chapters": {
    "1": {
      "pendingViews": 2,
      "lastIncrement": "2026-01-21T19:37:20.334Z",
      "lastUpdate": "2026-01-19T00:16:03+07:00"
    },
    "2": {
      "pendingViews": 1,
      "lastIncrement": "2026-01-21T19:41:53.687Z",
      "lastUpdate": "2026-01-17T00:23:06+07:00"
    },
    "3": {
      "pendingViews": 1,
      "lastIncrement": "2026-01-21T19:45:11.826Z",
      "lastUpdate": "2026-01-15T00:25:51+07:00"
    },
    "4": {
      "pendingViews": 1,
      "lastIncrement": "2026-01-21T19:47:59.830Z",
      "lastUpdate": "2026-01-20T00:22:28+07:00"
    },
    "7": {
      "pendingViews": 0,
      "lastIncrement": "2026-01-19T06:02:50.843Z",
      "lastUpdate": "2026-01-20T00:22:28+07:00"
    },
    "8": {
      "pendingViews": 3,
      "lastIncrement": "2026-01-21T12:00:13.028Z",
      "lastUpdate": "2026-01-20T00:22:28+07:00"
    },
    "5.1": {
      "pendingViews": 1,
      "lastIncrement": "2026-01-21T19:50:18.913Z",
      "lastUpdate": "2026-01-15T00:25:51+07:00"
    },
    "5.2": {
      "pendingViews": 1,
      "lastIncrement": "2026-01-21T19:51:42.854Z",
      "lastUpdate": "2026-01-20T00:22:28+07:00"
    },
    "5.5": {
      "pendingViews": 1,
      "lastIncrement": "2026-01-21T19:53:27.555Z",
      "lastUpdate": "2026-01-15T00:25:51+07:00"
    },
    "6.1": {
      "pendingViews": 1,
      "lastIncrement": "2026-01-21T19:54:14.724Z",
      "lastUpdate": "2026-01-16T00:30:18+07:00"
    },
    "6.2": {
      "pendingViews": 1,
      "lastIncrement": "2026-01-21T19:54:46.192Z",
      "lastUpdate": "2026-01-20T00:22:28+07:00"
    }
  },
  "lastUpdated": "2026-01-20T00:22:27+07:00"
}